[{"title":"1","content":"1","viewCount":1,"createdDate":1643001031055},{"title":"2","content":"2","viewCount":0,"createdDate":1643001032984},{"title":"3","content":"3","viewCount":0,"createdDate":1643001035227},{"title":"4","content":"4","viewCount":0,"createdDate":1643001037701},{"title":"5","content":"5","viewCount":0,"createdDate":1643001039997},{"title":"6","content":"6","viewCount":0,"createdDate":1643001042195},{"title":"7","content":"7","viewCount":0,"createdDate":1643097203466},{"title":"8","content":"8","viewCount":0,"createdDate":1643097212113}]